counterfactual/__init__.py
counterfactual/_nbdev.py
counterfactual/config.py
counterfactual/constants.py
counterfactual/data_handler.py
counterfactual/model.py
counterfactual-0.0.1.dist-info/METADATA
counterfactual-0.0.1.dist-info/WHEEL
counterfactual-0.0.1.dist-info/entry_points.txt
counterfactual-0.0.1.dist-info/top_level.txt
counterfactual-0.0.1.dist-info/RECORD
